fortniteapi/__init__.py
fortniteapi/tracker.py
fortniteapi-1.1.1.dist-info/DESCRIPTION.rst
fortniteapi-1.1.1.dist-info/METADATA
fortniteapi-1.1.1.dist-info/RECORD
fortniteapi-1.1.1.dist-info/WHEEL
fortniteapi-1.1.1.dist-info/metadata.json
fortniteapi-1.1.1.dist-info/top_level.txt
